my_mltools/__init__.py
my_mltools/cat_encode.py
my_mltools/check_utils.py
my_mltools/cleaning_utils.py
my_mltools/exceptions.py
my_mltools/geospatial.py
my_mltools-0.6.0.dist-info/LICENSE
my_mltools-0.6.0.dist-info/WHEEL
my_mltools-0.6.0.dist-info/METADATA
my_mltools-0.6.0.dist-info/RECORD
