Metadata-Version: 2.1
Name: my-mltools
Version: 0.6.0
Summary: My machine learning toolkit.
License: MIT
Author: Yang Wu
Requires-Python: >=3.8,<3.11
Classifier: License :: OSI Approved :: MIT License
Classifier: Programming Language :: Python :: 3
Classifier: Programming Language :: Python :: 3.10
Classifier: Programming Language :: Python :: 3.8
Classifier: Programming Language :: Python :: 3.9
Requires-Dist: kneed (>=0.7.0,<0.8.0)
Requires-Dist: pandas (>=1.4.2,<2.0.0)
Requires-Dist: scikit-learn (>=1.0.2,<2.0.0)
Requires-Dist: tensorflow (>=2.8.0,<3.0.0)
Requires-Dist: yellowbrick (>=1.4,<2.0)
